jbtsdk
